[{"x":"152px","y":"144px","content":"<h1>Hello</h1>","sequence":1,"width":"150px","height":"100px"},{"x":"343px","y":"236px","content":"<p>This is a second node </p>e","sequence":2,"width":"275px","height":"165px"},{"x":"427px","y":"458px","content":"<p>YAYY</p>","sequence":3,"width":"150px","height":"100px"},{"x":"154px","y":"353px","content":"<p>New Node</p>","sequence":4,"width":"150px","height":"100px"},{"x":"379px","y":"604px","content":"<p>New Node</p>","sequence":5,"width":"150px","height":"100px"},{"x":"627px","y":"106px","content":"<p>New Node</p>","sequence":6,"width":"150px","height":"100px"},{"x":"720px","y":"550px","content":"e<p>New Node</p>","sequence":7,"width":"150px","height":"100px"}]